MANIFEST.in
README.rst
setup.py
grvlms_ecommerce.egg-info/PKG-INFO
grvlms_ecommerce.egg-info/SOURCES.txt
grvlms_ecommerce.egg-info/dependency_links.txt
grvlms_ecommerce.egg-info/entry_points.txt
grvlms_ecommerce.egg-info/requires.txt
grvlms_ecommerce.egg-info/top_level.txt
grvlmsecommerce/__about__.py
grvlmsecommerce/__init__.py
grvlmsecommerce/plugin.py
grvlmsecommerce/patches/https-create
grvlmsecommerce/patches/k8s-deployments
grvlmsecommerce/patches/k8s-deployments-nginx-init-containers
grvlmsecommerce/patches/k8s-deployments-nginx-volume-mounts
grvlmsecommerce/patches/k8s-deployments-nginx-volumes
grvlmsecommerce/patches/k8s-ingress-rules
grvlmsecommerce/patches/k8s-ingress-tls-hosts
grvlmsecommerce/patches/k8s-jobs
grvlmsecommerce/patches/k8s-services
grvlmsecommerce/patches/kustomization-configmapgenerator
grvlmsecommerce/patches/local-docker-compose-nginx-volumes
grvlmsecommerce/patches/local-docker-compose-services
grvlmsecommerce/patches/nginx-extra
grvlmsecommerce/patches/openedx-lms-common-settings
grvlmsecommerce/templates/ecommerce/apps/grvlms.py
grvlmsecommerce/templates/ecommerce/apps/grvlms_worker.py
grvlmsecommerce/templates/ecommerce/build/ecommerce/Dockerfile
grvlmsecommerce/templates/ecommerce/build/ecommerce/assets.py
grvlmsecommerce/templates/ecommerce/build/ecommerce-worker/Dockerfile
grvlmsecommerce/templates/ecommerce/hooks/ecommerce/init
grvlmsecommerce/templates/ecommerce/hooks/lms/init
grvlmsecommerce/templates/ecommerce/hooks/mysql/init