Metadata-Version: 1.2
Name: grvlms-ecommerce
Version: 1.0.3
Summary: Ecommerce plugin for Grvlms
Home-page: https://docs.grvlms.groove.education/
Author: GrooveTechnology
Author-email: thuan.ha@groovetechnology.com
License: AGPLv3
Project-URL: Documentation, https://docs.grvlms.groove.education
Project-URL: Code, https://github.com/groovetch/grvlms-ecommerce
Project-URL: Issue tracker, https://github.com/groovetch/grvlms-ecommerce/issues
Project-URL: Community, https://groove.education
Platform: UNKNOWN
Classifier: Development Status :: 5 - Production/Stable
Classifier: Intended Audience :: Developers
Classifier: License :: OSI Approved :: GNU Affero General Public License v3
Classifier: Operating System :: OS Independent
Classifier: Programming Language :: Python
Classifier: Programming Language :: Python :: 3.5
Classifier: Programming Language :: Python :: 3.6
Classifier: Programming Language :: Python :: 3.7
Requires-Python: >=3.5
